django_drf_async/__init__.py
django_drf_async/api_view.py
django_drf_async/generics.py
django_drf_async/mixins.py
django_drf_async/request.py
django_drf_async/services/__init__.py
django_drf_async/services/base.py
django_drf_async-0.1.0.dist-info/METADATA
django_drf_async-0.1.0.dist-info/WHEEL
django_drf_async-0.1.0.dist-info/RECORD
