Metadata-Version: 2.1
Name: django-drf-async
Version: 0.1.0
Summary: 
Author: godd0t
Author-email: lirrishala@gmail.com
Requires-Python: >=3.10,<4.0
Classifier: Programming Language :: Python :: 3
Classifier: Programming Language :: Python :: 3.10
Classifier: Programming Language :: Python :: 3.11
Requires-Dist: django (>=4.1.5,<5.0.0)
Requires-Dist: djangorestframework (>=3.14.0,<4.0.0)
